CHANGES.txt
README.txt
eggtestinfo.py
setup.py
test_egginfo.py
eggtestinfo.egg-info/PKG-INFO
eggtestinfo.egg-info/SOURCES.txt
eggtestinfo.egg-info/dependency_links.txt
eggtestinfo.egg-info/entry_points.txt
eggtestinfo.egg-info/test_info.txt
eggtestinfo.egg-info/top_level.txt
eggtestinfo.egg-info/zip-safe