Metadata-Version: 1.0
Name: eggtestinfo
Version: 0.3
Summary: Add test information to .egg-info
Home-page: http://pypi.python.org/pypi/eggtestinfo
Author: Tres Seaver
Author-email: tseaver@palladion.com
License: PSF or ZPL
Keywords: setuptools eggs testing
Platform: UNKNOWN
Classifier: Development Status :: 3 - Alpha
Classifier: Framework :: Setuptools Plugin
Classifier: Intended Audience :: Developers
Classifier: License :: OSI Approved :: Python Software Foundation License
Classifier: License :: OSI Approved :: Zope Public License
Classifier: Operating System :: OS Independent
Classifier: Programming Language :: Python :: 2
Classifier: Programming Language :: Python :: 3
Classifier: Topic :: Software Development :: Libraries :: Python Modules
Classifier: Topic :: System :: Archiving :: Packaging
